MANIFEST.in
README
setup.py
DoapView/DoapView.py
DoapView/__init__.py
DoapView/templates/doap.html
DoapViewPlugin.egg-info/PKG-INFO
DoapViewPlugin.egg-info/SOURCES.txt
DoapViewPlugin.egg-info/dependency_links.txt
DoapViewPlugin.egg-info/entry_points.txt
DoapViewPlugin.egg-info/requires.txt
DoapViewPlugin.egg-info/top_level.txt
DoapViewPlugin.egg-info/zip-safe