Metadata-Version: 1.0
Name: DoapViewPlugin
Version: 0.2
Summary: Renders DOAP (Description of a Project) RDF in a Trac wiki
Home-page: http://trac-hacks.org/wiki/DoapViewMacro
Author: Rob Cakebread
Author-email: cakebread@gmail.com
License: GPL-2
Keywords: doap rdf trac foaf
Platform: UNKNOWN
Classifier: Development Status :: 2 - Pre-Alpha
Classifier: Framework :: Trac
Classifier: Intended Audience :: Developers
Classifier: Intended Audience :: End Users/Desktop
Classifier: License :: OSI Approved :: BSD License
Classifier: Programming Language :: Python
Classifier: Topic :: Software Development :: Libraries :: Python Modules
